pynicolet/__init__.py
pynicolet/data.py
pynicolet/events.py
pynicolet/header.py
pynicolet/reader.py
pynicolet-0.1.1.dist-info/licenses/LICENSE
pynicolet-0.1.1.dist-info/METADATA
pynicolet-0.1.1.dist-info/WHEEL
pynicolet-0.1.1.dist-info/top_level.txt
pynicolet-0.1.1.dist-info/RECORD
