Metadata-Version: 2.4
Name: pynicolet
Version: 0.1.1
Summary: A lightweight Python library for reading legacy Nicolet EEG files
Author-email: Nathan Soares de Melo <nathan.soares@ensae.fr>
License: MIT License
Project-URL: Repository, https://github.com/NathENSAE/pynicolet
Project-URL: Issues, https://github.com/NathENSAE/pynicolet/issues
Classifier: Development Status :: 4 - Beta
Classifier: Intended Audience :: Science/Research
Classifier: Intended Audience :: Healthcare Industry
Classifier: License :: OSI Approved :: MIT License
Classifier: Programming Language :: Python :: 3
Classifier: Programming Language :: Python :: 3.8
Classifier: Programming Language :: Python :: 3.9
Classifier: Programming Language :: Python :: 3.10
Classifier: Programming Language :: Python :: 3.11
Classifier: Operating System :: OS Independent
Classifier: Topic :: Scientific/Engineering :: Medical Science Apps.
Requires-Python: >=3.8
License-File: LICENSE
Requires-Dist: numpy
Requires-Dist: tqdm
Provides-Extra: dev
Requires-Dist: matplotlib; extra == "dev"
Requires-Dist: build; extra == "dev"
Requires-Dist: twine; extra == "dev"
Dynamic: license-file
